bmad_mcp/__init__.py
bmad_mcp/resources.py
bmad_mcp/server.py
bmad_mcp/embedded/_cfg/agent-manifest.csv
bmad_mcp/embedded/_cfg/files-manifest.csv
bmad_mcp/embedded/_cfg/manifest.yaml
bmad_mcp/embedded/_cfg/task-manifest.csv
bmad_mcp/embedded/_cfg/workflow-manifest.csv
bmad_mcp/embedded/_cfg/agents/bmm-analyst.customize.yaml
bmad_mcp/embedded/_cfg/agents/bmm-architect.customize.yaml
bmad_mcp/embedded/_cfg/agents/bmm-dev.customize.yaml
bmad_mcp/embedded/_cfg/agents/bmm-game-architect.customize.yaml
bmad_mcp/embedded/_cfg/agents/bmm-game-designer.customize.yaml
bmad_mcp/embedded/_cfg/agents/bmm-game-dev.customize.yaml
bmad_mcp/embedded/_cfg/agents/bmm-pm.customize.yaml
bmad_mcp/embedded/_cfg/agents/bmm-sm.customize.yaml
bmad_mcp/embedded/_cfg/agents/bmm-tea.customize.yaml
bmad_mcp/embedded/_cfg/agents/bmm-ux-expert.customize.yaml
bmad_mcp/embedded/_cfg/agents/core-bmad-master.customize.yaml
bmad_mcp/embedded/bmm/README.md
bmad_mcp/embedded/bmm/config.yaml
bmad_mcp/embedded/bmm/agents/analyst.md
bmad_mcp/embedded/bmm/agents/architect.md
bmad_mcp/embedded/bmm/agents/dev.md
bmad_mcp/embedded/bmm/agents/game-architect.md
bmad_mcp/embedded/bmm/agents/game-designer.md
bmad_mcp/embedded/bmm/agents/game-dev.md
bmad_mcp/embedded/bmm/agents/pm.md
bmad_mcp/embedded/bmm/agents/sm.md
bmad_mcp/embedded/bmm/agents/tea.md
bmad_mcp/embedded/bmm/agents/ux-expert.md
bmad_mcp/embedded/bmm/tasks/daily-standup.xml
bmad_mcp/embedded/bmm/tasks/retrospective.xml
bmad_mcp/embedded/bmm/teams/team-all.yaml
bmad_mcp/embedded/bmm/teams/team-gamedev.yaml
bmad_mcp/embedded/bmm/teams/team-planning.yaml
bmad_mcp/embedded/bmm/testarch/README.md
bmad_mcp/embedded/bmm/testarch/tea-index.csv
bmad_mcp/embedded/bmm/testarch/knowledge/ci-burn-in.md
bmad_mcp/embedded/bmm/testarch/knowledge/component-tdd.md
bmad_mcp/embedded/bmm/testarch/knowledge/contract-testing.md
bmad_mcp/embedded/bmm/testarch/knowledge/data-factories.md
bmad_mcp/embedded/bmm/testarch/knowledge/email-auth.md
bmad_mcp_server-0.1.1.dist-info/METADATA
bmad_mcp_server-0.1.1.dist-info/WHEEL
bmad_mcp_server-0.1.1.dist-info/entry_points.txt
bmad_mcp_server-0.1.1.dist-info/licenses/LICENSE
bmad_mcp_server-0.1.1.dist-info/RECORD
