Metadata-Version: 2.4
Name: bmad-mcp-server
Version: 0.1.1
Summary: MCP server providing BMad Master orchestration with embedded agent personas, workflows, and task execution capabilities
Project-URL: Homepage, https://github.com/mkellerman/bmad-mcp-server
Project-URL: Repository, https://github.com/mkellerman/bmad-mcp-server
Project-URL: Documentation, https://github.com/mkellerman/bmad-mcp-server#readme
Project-URL: Issues, https://github.com/mkellerman/bmad-mcp-server/issues
Author-email: Marc R Kellerman <mkellerman@outlook.com>
License: MIT
License-File: LICENSE
Keywords: agent,bmad,claude,mcp,orchestration,personas,server,workflow
Classifier: Development Status :: 3 - Alpha
Classifier: Intended Audience :: Developers
Classifier: License :: OSI Approved :: MIT License
Classifier: Programming Language :: Python :: 3
Classifier: Programming Language :: Python :: 3.10
Classifier: Programming Language :: Python :: 3.11
Classifier: Programming Language :: Python :: 3.12
Classifier: Topic :: Scientific/Engineering :: Artificial Intelligence
Classifier: Topic :: Software Development :: Libraries :: Python Modules
Requires-Python: >=3.10
Requires-Dist: mcp>=1.0.0
Requires-Dist: pyyaml>=6.0.1
